{
    "checksum": "2f4d7fac051c0236c76bb34d3bacdc52",
    "wallpaper": "/home/kirk/Pictures/Wallpapers/cat-fantasy-city.jpg",
    "alpha": "100",
    "special": {
        "background": "#0e1122",
        "foreground": "#c2c3c7",
        "cursor": "#c2c3c7"
    },
    "colors": {
        "color0": "#0e1122",
        "color1": "#717489",
        "color2": "#887B8D",
        "color3": "#7E8195",
        "color4": "#9C93A4",
        "color5": "#DEAAAA",
        "color6": "#E3CDB5",
        "color7": "#c2c3c7",
        "color8": "#5e6172",
        "color9": "#717489",
        "color10": "#887B8D",
        "color11": "#7E8195",
        "color12": "#9C93A4",
        "color13": "#DEAAAA",
        "color14": "#E3CDB5",
        "color15": "#c2c3c7"
    }
}