{
    "checksum": "8e48b4aeda885a70bb84c54a915c2f66",
    "wallpaper": "/home/kirk/Downloads/walls-main/ General-Wallpapers/mathew-macquarrie-Lzx4J_Pb3sk-unsplash.jpg",
    "alpha": "100",
    "special": {
        "background": "#20200d",
        "foreground": "#c7c7c2",
        "cursor": "#c7c7c2"
    },
    "colors": {
        "color0": "#20200d",
        "color1": "#949032",
        "color2": "#A29957",
        "color3": "#C7BF6B",
        "color4": "#6A8DA8",
        "color5": "#6EAAD0",
        "color6": "#A39D9D",
        "color7": "#c7c7c2",
        "color8": "#71715d",
        "color9": "#949032",
        "color10": "#A29957",
        "color11": "#C7BF6B",
        "color12": "#6A8DA8",
        "color13": "#6EAAD0",
        "color14": "#A39D9D",
        "color15": "#c7c7c2"
    }
}